chaparralapi/__init__.py
chaparralapi/client.py
chaparralapi/constants.py
chaparralapi/search_config_builder.py
chaparralapi/utils.py
chaparralapi/models/__init__.py
chaparralapi/models/database.py
chaparralapi/models/organization.py
chaparralapi/models/organization_usage.py
chaparralapi/models/profile.py
chaparralapi/models/project.py
chaparralapi/models/project_file.py
chaparralapi/models/search_config.py
chaparralapi/models/search_result.py
chaparralapi/models/search_result_download.py
chaparralapi/models/search_result_qc.py
chaparralapi/routes/__init__.py
chaparralapi/routes/base.py
chaparralapi/routes/databases.py
chaparralapi/routes/organization.py
chaparralapi/routes/organization_invite.py
chaparralapi/routes/organization_usage.py
chaparralapi/routes/profile.py
chaparralapi/routes/project.py
chaparralapi/routes/project_file.py
chaparralapi/routes/search_result_qc.py
chaparralapi/routes/search_results.py
chaparralapi/routes/search_results_download.py
tests/__init__.py
tests/test_client_mock.py
chaparralapi-0.1.1.dist-info/METADATA
chaparralapi-0.1.1.dist-info/WHEEL
chaparralapi-0.1.1.dist-info/top_level.txt
chaparralapi-0.1.1.dist-info/RECORD
