Metadata-Version: 2.1
Name: chaparralapi
Version: 0.1.1
Summary: An API for the Chaparral platform
Author-email: Patrick Garrett <pgarrett@scripps.edu>
Keywords: chaparral,api,bioinformatics
Classifier: Programming Language :: Python :: 3
Classifier: Programming Language :: Python :: 3.8
Classifier: Programming Language :: Python :: 3.9
Classifier: Programming Language :: Python :: 3.10
Classifier: Programming Language :: Python :: 3.11
Classifier: Programming Language :: Python :: 3.12
Classifier: Development Status :: 4 - Beta
Classifier: License :: OSI Approved :: MIT License
Classifier: Operating System :: OS Independent
Requires-Python: >=3.8
Requires-Dist: requests >=2.31.0
Requires-Dist: pydantic >=2.7.1
Requires-Dist: pydantic[email] >=2.7.1
Requires-Dist: ping3 >=4.0.8
Provides-Extra: test
Requires-Dist: pytest >=6.2 ; extra == 'test'
Requires-Dist: pytest-mock >=3.6 ; extra == 'test'
